fxparser/__init__.py
fxparser/actionParser.py
fxparser/assets/forexlist.json
fxparser/assets/saved_model.pb
fxparser/baseParser.py
fxparser/flagParser.py
fxparser/parserHelper.py
fxparser/priceParser.py
fxparser/slParser.py
fxparser/symbolParser.py
fxparser/tpParser.py
fxparser/urgencyParser.py
fxparser-2.3.6.dist-info/LICENSE
fxparser-2.3.6.dist-info/WHEEL
fxparser-2.3.6.dist-info/METADATA
fxparser-2.3.6.dist-info/RECORD
